drifter/__init__.py
drifter/apps.py
drifter/management/__init__.py
drifter/management/commands/__init__.py
drifter/management/commands/redo_migration.py
drifter/management/commands/reset_database.py
drifter/management/commands/revert_migration.py
django_drifter-0.1.2.dist-info/LICENSE.txt
django_drifter-0.1.2.dist-info/WHEEL
django_drifter-0.1.2.dist-info/METADATA
django_drifter-0.1.2.dist-info/RECORD
